Workbook
Name AssignedTo: Masters!$W$2:$W$8
Name CFOApproval: Masters!$O$2:$O$4
Name Consulting: Masters!$AK$2:$AK$4
Name Cybersecurity: Masters!$AM$2:$AM$2
Name DealStage: Masters!$C$2:$C$6
Name Finance: Masters!$AG$2:$AG$3
Name InvoiceStatus: Masters!$K$2:$K$6
Name InvoiceTerms: Masters!$AO$2:$AO$4
Name InvoiceType: Masters!$M$2:$M$4
Name LeadSource: Masters!$Y$2:$Y$9
Name LeadStatus: Masters!$A$2:$A$8
Name Marketing: Masters!$AE$2:$AE$4
Name PaymentCadence: Masters!$G$2:$G$6
Name PaymentStatus: Masters!$I$2:$I$4
Name POStatus: Masters!$S$2:$S$4
Name PostSales: Masters!$AC$2:$AC$4
Name POValidated: Masters!$U$2:$U$3
Name PreSales: Masters!$AA$2:$AA$4
Name ReminderStatus: Masters!$Q$2:$Q$5
Name ServicePillar: Masters!$E$2:$E$8
Name Software_Dev: Masters!$AI$2:$AI$4

Sheet Masters
A1: Lead Status | C1: Deal Sales Stage | E1: Service Pillar / Category | G1: Payment Cadence | I1: Payment Status | K1: Invoice Status | M1: Invoice Type | O1: CFO Approval | Q1: Reminder Status | S1: PO Status | U1: PO Validated | W1: Assigned To | Y1: Lead Source | AA1: PreSales | AC1: PostSales | AE1: Marketing | AG1: Finance | AI1: Software Dev | AK1: Consulting | AM1: Cybersecurity | AO1: Invoice Terms
A2: Lead Generation | C2: Commercial Proposal | E2: PreSales | G2: Advance | I2: Pending | K2: Invoice Draft | M2: Advance | O2: Pending | Q2: None | S2: Active | U2: Yes | W2: Praveen Sahai | Y2: Website | AA2: Resources | AC2: Resources | AE2: Brand Assets | AG2: Cashflow Finance | AI2: Agentic Tool | AK2: Growth Advisory | AM2: Cyber Security | AO2: Immediate
A3: Lead Qualification | C3: Negotiation | E3: PostSales | G3: Milestone | I3: Partially Paid | K3: CFO Approval Pending | M3: Milestone | O3: Approved | Q3: 1st Reminder | S3: Completed | U3: No | W3: Arunava Chakrabarty | Y3: Referral | AA3: Training | AC3: Training | AE3: CMO Services | AG3: Bill Discounting | AI3: CMS / CLM | AK3: FinOps/Biz Ops | AO3: Net 30
A4: Assign | C4: Win | E4: Marketing | G4: Monthly | I4: Paid | K4: Invoice Sent | M4: Final | O4: Rejected | Q4: 2nd Reminder | S4: Cancelled | W4: Dilip Sundaram | Y4: LinkedIn | AA4: BidBrain | AC4: BidBrain | AE4: ICP & ABM | AI4: Resources | AK4: Consulting Agentic Tool | AO4: Net 45
A5: First Contact | C5: Lost | E5: Finance | G5: Quarterly | K5: Payment Pending | Q5: Escalated | W5: Asif Bhat | Y5: Cold Call
A6: Discovery Meeting | C6: Cancel | E6: Software Dev | G6: Final Payment | K6: Payment Received | W6: Tarun Shiroley | Y6: Email Campaign
A7: Approach or Demo | E7: Consulting | W7: Hemant Tathod | Y7: Event
A8: Converted | E8: Cybersecurity | W8: Saji Mathew | Y8: Partner
A9: Cancelled | Y9: Other

Sheet Enquiry
A1: Lead Number | B1: Lead Name | C1: Company Name | D1: Contact Name | E1: Service Pillar | F1: Sub Category | G1: Assigned To | H1: Lead Source | I1: Status | J1: Comments | K1: Created Date
A2: 💡 Lead Number auto-generates when Lead Name is entered. Use dropdowns for Pillar, Sub-Category, Assigned To, Source, and Status.
A3: L001 | B3: CitiusCloud Services | C3: CitiusCloud Services | D3: Roshan Shetty | E3: Consulting | F3: Growth Advisory | G3: Arunava Chakrabarty | H3: Cold Call | I3: Converted | J3: Proposal Sent 22/08/2025 11:28 AM By: | K3: 45891
A4: L002 | B4: Galaxy | C4: Galaxy Office Automation Pvt Ltd | D4: Anoop PaiDhungat | E4: Software Dev | F4: Resources | G4: Asif | H4: Partner | I4: Converted | J4: "2 AI Engineers with 5+ years experience; 2 profiles shared 22/08/2025 11:28 AM By: " | K4: 45892
A5: L003 | B5: Nutanix | C5: Nutanix India Pvt Ltd | D5: Renu Asrani | E5: Marketing | F5: ICP & ABM | G5: Avinash | H5: Partner | I5: Converted | J5: "ABM pilot for Top 40-45 accounts 22/08/2025 11:28 AM By: " | K5: 45893
A6: L004 | B6: ARCA Alternatives | C6: ARCA Alternatives | D6: Sagar Nagaraj | E6: Marketing | F6: ICP & ABM | G6: Avinash | H6: Partner | I6: Cancelled | J6: "Demo done on June 6th; Demo account to be created 22/08/2025 11:28 AM By: " | K6: 45894
A7: L005 | B7: Azentio | C7: Azentio | D7: Vamsi Chaitanya | E7: Marketing | F7: ICP & ABM | G7: Avinash | H7: Partner | I7: Cancelled | J7: "Demo pending - to be scheduled 22/08/2025 11:28 AM By: " | K7: 45894
A8: L006 | B8: Checkpoint | C8: Checkpoint Software | D8: Keely Wilkins | E8: Marketing | F8: ICP & ABM | G8: Avinash | H8: Partner | I8: Converted | J8: "Demo pending - to be scheduled 22/08/2025 11:28 AM By: " | K8: 45894
A9: L007 | B9: Galaxy | C9: Galaxy Office Automation Pvt Ltd | D9: Grishma Potdar | E9: Marketing | F9: Brand Assets | G9: Anand/Shruti | H9: Partner | I9: Approach or Demo | J9: "ICP/ABM for Insurance sector for Checkpoint cyberinsurance alliances 22/08/2025 11:28 AM By: " | K9: 45894
A10: L008 | B10: TechMahindra Consult | C10: TechMahindra Ltd | D10: Anil Sharma | E10: Consulting | F10: Growth Advisory | G10: Praveen Sahai | H10: Referral | I10: Converted | J10: Proposal sent and accepted | K10: 45667
A11: L009 | B11: Wipro AI Project | C11: Wipro Technologies Ltd | D11: Sneha Kapoor | E11: Software Dev | F11: Agentic Tool | G11: Asif Bhat | H11: Partner | I11: Converted | J11: AI tool development deal signed | K11: 45675
A12: L010 | B12: Infosys Cyber Shield | C12: Infosys BPM Ltd | D12: Rahul Menon | E12: Cybersecurity | F12: Cyber Security | G12: Dilip Sundaram | H12: Cold Call | I12: Converted | J12: Security audit and monitoring | K12: 45693
A13: L011 | B13: HCL Brand Relaunch | C13: HCL Technologies | D13: Priya Nair | E13: Marketing | F13: Brand Assets | G13: Avinash | H13: Event | I13: Converted | J13: Full brand relaunch project | K13: 45702
A14: L012 | B14: Reliance FinOps | C14: Reliance Industries | D14: Amit Gupta | E14: Finance | F14: FinOps/Biz Ops | G14: Saji Mathew | H14: LinkedIn | I14: Converted | J14: FinOps transformation | K14: 45718
... A49: L047 | B49: Meesho Growth Consult | C49: Fashnear Technologies Pvt Ltd | D49: Preet Shah | E49: Consulting | F49: FinOps/Biz Ops | G49: Praveen Sahai | H49: Email Campaign | I49: Lead Generation | J49: Enquiry received today via email | K49: 46087
K50: =IF(B50="","",TODAY())
A51: =IF(B51="","","L"&TEXT(ROW()-2,"000")) | K51: =IF(B51="","",TODAY())
A52: =IF(B52="","","L"&TEXT(ROW()-2,"000")) | K52: =IF(B52="","",TODAY())
A53: =IF(B53="","","L"&TEXT(ROW()-2,"000")) | K53: =IF(B53="","",TODAY())
A54: =IF(B54="","","L"&TEXT(ROW()-2,"000")) | K54: =IF(B54="","",TODAY())
A55: =IF(B55="","","L"&TEXT(ROW()-2,"000")) | K55: =IF(B55="","",TODAY())
A56: =IF(B56="","","L"&TEXT(ROW()-2,"000")) | K56: =IF(B56="","",TODAY())
A57: =IF(B57="","","L"&TEXT(ROW()-2,"000")) | K57: =IF(B57="","",TODAY())
A58: =IF(B58="","","L"&TEXT(ROW()-2,"000")) | K58: =IF(B58="","",TODAY())
A59: =IF(B59="","","L"&TEXT(ROW()-2,"000")) | K59: =IF(B59="","",TODAY())
A60: =IF(B60="","","L"&TEXT(ROW()-2,"000")) | K60: =IF(B60="","",TODAY())
A61: =IF(B61="","","L"&TEXT(ROW()-2,"000")) | K61: =IF(B61="","",TODAY())
A62: =IF(B62="","","L"&TEXT(ROW()-2,"000")) | K62: =IF(B62="","",TODAY())
... A502: =IF(B502="","","L"&TEXT(ROW()-2,"000")) | K502: =IF(B502="","",TODAY())

Sheet Deal
A1: Deal ID (Lead No.) | B1: Company Name | C1: Contact Name | D1: Service Pillar | E1: Expected Amount | F1: Negotiated Amount | G1: Expected Close Date | H1: Sales Stage | I1: Assigned To | J1: Comments | K1: PO Ready?
A2: 💡 Enter Deal ID from Enquiry. PO Ready? flag auto-shows when Sales Stage = Win. Use that Deal ID in PO_Workflow to generate the PO.
A3: {=IFERROR(INDEX(Enquiry!$A:$A, SMALL(IF(Enquiry!$I$3:$I$502="Converted", ROW(Enquiry!$I$3:$I$502)),1) ),"")} -> L001 | B3: CitiusCloud Services | C3: Roshan Shetty | D3: Consulting | E3: 600000 | F3: 600000 | G3: 45919 | H3: Win | I3: Arunava Chakrabarty | J3: "Payment Type: Monthly (Variable) Phases: Phase 1: Rs. 2,00,000/- (2025-10-01 to 2025-12-31) Notes: Retainer contract 30/09/2025 11:37 AM By: Arunava Chakrabarty ======================================== Updated Commercial proposal for 3 months pilot @ Rs 2,00,000 lakhs per month starting October 1, 2025 11/09/2025 01:11 PM By: Arunava Chakrabarty ======================================== Rs. 200000 per month for 3 years 25/08/2025 05:58 AM By: Arunava Chakrabarty ======================================== Proposal Sent 22/08/2025 11:28 AM By: " | K3: ✅ Move to PO Workflow
A4: L002 | B4: Galaxy Office Automation Pvt Ltd | C4: Anoop PaiDhungat | D4: Software Dev | E4: 4800000 | F4: 3600000 | G4: 45899 | H4: Cancel | I4: Asif Bhat | J4: 2 AI Engineers; deal cancelled due to budget | K4: ⬜ Not Won Yet
A5: L003 | B5: Nutanix India Pvt Ltd | C5: Renu Asrani | D5: Marketing | E5: 1700000 | F5: 1400000 | G5: 45899 | H5: Cancel | I5: Avinash | J5: ABM pilot cancelled - no budget approval | K5: ⬜ Not Won Yet
A6: L006 | B6: Checkpoint Software | C6: Keely Wilkins | D6: Marketing | E6: 1423740 | F6: 1200000 | G6: 45915 | H6: Lost | I6: Avinash | J6: Lost to competitor on pricing | K6: ⬜ Not Won Yet
A7: L001 | B7: CitiusCloud Services | C7: Roshan Shetty | D7: Consulting | E7: 600000 | F7: 600000 | G7: 45919 | H7: Win | I7: Arunava Chakrabarty | J7: Duplicate entry - retainer confirmed | K7: ✅ Move to PO Workflow
A8: L008 | B8: TechMahindra Ltd | C8: Anil Sharma | D8: Consulting | E8: 1200000 | F8: 1100000 | G8: 45747 | H8: Win | I8: Praveen Sahai | J8: Monthly consulting retainer | K8: ✅ Move to PO Workflow
A9: L009 | B9: Wipro Technologies Ltd | C9: Sneha Kapoor | D9: Software Dev | E9: 4200000 | F9: 3800000 | G9: 45777 | H9: Win | I9: Asif Bhat | J9: AI tool dev - 6 month project | K9: ✅ Move to PO Workflow
A10: L010 | B10: Infosys BPM Ltd | C10: Rahul Menon | D10: Cybersecurity | E10: 850000 | F10: 800000 | G10: 45792 | H10: Win | I10: Dilip Sundaram | J10: Cybersecurity audit quarterly | K10: ✅ Move to PO Workflow
A11: L011 | B11: HCL Technologies | C11: Priya Nair | D11: Marketing | E11: 2500000 | F11: 2200000 | G11: 45838 | H11: Win | I11: Avinash | J11: Full brand relaunch | K11: ✅ Move to PO Workflow
A12: L012 | B12: Reliance Industries | C12: Amit Gupta | D12: Finance | E12: 950000 | F12: 900000 | G12: 45853 | H12: Win | I12: Saji Mathew | J12: FinOps transformation Q2 | K12: ✅ Move to PO Workflow
A13: L013 | B13: Tata Consultancy Services | C13: Deepa Iyer | D13: Software Dev | E13: 3200000 | F13: 2900000 | G13: 45869 | H13: Win | I13: Tarun Shiroley | J13: CMS integration 9 months | K13: ✅ Move to PO Workflow
A14: L014 | B14: HDFC Bank Ltd | C14: Sanjay Pillai | D14: Marketing | E14: 1800000 | F14: 1600000 | G14: 45900 | H14: Win | I14: Avinash | J14: ABM pilot BFSI sector | K14: ✅ Move to PO Workflow
A15: L015 | B15: Accenture Solutions Pvt Ltd | C15: Monica Verma | D15: PreSales | E15: 600000 | F15: 600000 | G15: 45930 | H15: Win | I15: Hemant Tathod | J15: Training program 3 months | K15: ✅ Move to PO Workflow
... A32: L043 | B32: Groww Invest Tech Pvt Ltd | C32: Nisha Kapoor | D32: PostSales | E32: 780000 | F32: 680000 | G32: 46112 | H32: Negotiation | I32: Avinash | J32: ABM demo done, proposal pending | K32: ⬜ Not Won Yet
B33: =IF($A33="","",IFERROR(VLOOKUP($A33,Enquiry!$A:$K,3,0),"-")) | C33: =IF($A33="","",IFERROR(VLOOKUP($A33,Enquiry!$A:$K,4,0),"-")) | D33: =IF($A33="","",IFERROR(VLOOKUP($A33,Enquiry!$A:$K,5,0),"-")) | K33: =IF(A33="","",IF(H33="Win","✅ Move to PO Workflow","⬜ Not Won Yet"))
B34: =IF($A34="","",IFERROR(VLOOKUP($A34,Enquiry!$A:$K,3,0),"-")) | C34: =IF($A34="","",IFERROR(VLOOKUP($A34,Enquiry!$A:$K,4,0),"-")) | D34: =IF($A34="","",IFERROR(VLOOKUP($A34,Enquiry!$A:$K,5,0),"-")) | K34: =IF(A34="","",IF(H34="Win","✅ Move to PO Workflow","⬜ Not Won Yet"))
B35: =IF($A35="","",IFERROR(VLOOKUP($A35,Enquiry!$A:$K,3,0),"-")) | C35: =IF($A35="","",IFERROR(VLOOKUP($A35,Enquiry!$A:$K,4,0),"-")) | D35: =IF($A35="","",IFERROR(VLOOKUP($A35,Enquiry!$A:$K,5,0),"-")) | K35: =IF(A35="","",IF(H35="Win","✅ Move to PO Workflow","⬜ Not Won Yet"))
B36: =IF($A36="","",IFERROR(VLOOKUP($A36,Enquiry!$A:$K,3,0),"-")) | C36: =IF($A36="","",IFERROR(VLOOKUP($A36,Enquiry!$A:$K,4,0),"-")) | D36: =IF($A36="","",IFERROR(VLOOKUP($A36,Enquiry!$A:$K,5,0),"-")) | K36: =IF(A36="","",IF(H36="Win","✅ Move to PO Workflow","⬜ Not Won Yet"))
B37: =IF($A37="","",IFERROR(VLOOKUP($A37,Enquiry!$A:$K,3,0),"-")) | C37: =IF($A37="","",IFERROR(VLOOKUP($A37,Enquiry!$A:$K,4,0),"-")) | D37: =IF($A37="","",IFERROR(VLOOKUP($A37,Enquiry!$A:$K,5,0),"-")) | K37: =IF(A37="","",IF(H37="Win","✅ Move to PO Workflow","⬜ Not Won Yet"))
B38: =IF($A38="","",IFERROR(VLOOKUP($A38,Enquiry!$A:$K,3,0),"-")) | C38: =IF($A38="","",IFERROR(VLOOKUP($A38,Enquiry!$A:$K,4,0),"-")) | D38: =IF($A38="","",IFERROR(VLOOKUP($A38,Enquiry!$A:$K,5,0),"-")) | K38: =IF(A38="","",IF(H38="Win","✅ Move to PO Workflow","⬜ Not Won Yet"))
B39: =IF($A39="","",IFERROR(VLOOKUP($A39,Enquiry!$A:$K,3,0),"-")) | C39: =IF($A39="","",IFERROR(VLOOKUP($A39,Enquiry!$A:$K,4,0),"-")) | D39: =IF($A39="","",IFERROR(VLOOKUP($A39,Enquiry!$A:$K,5,0),"-")) | K39: =IF(A39="","",IF(H39="Win","✅ Move to PO Workflow","⬜ Not Won Yet"))
B40: =IF($A40="","",IFERROR(VLOOKUP($A40,Enquiry!$A:$K,3,0),"-")) | C40: =IF($A40="","",IFERROR(VLOOKUP($A40,Enquiry!$A:$K,4,0),"-")) | D40: =IF($A40="","",IFERROR(VLOOKUP($A40,Enquiry!$A:$K,5,0),"-")) | K40: =IF(A40="","",IF(H40="Win","✅ Move to PO Workflow","⬜ Not Won Yet"))
B41: =IF($A41="","",IFERROR(VLOOKUP($A41,Enquiry!$A:$K,3,0),"-")) | C41: =IF($A41="","",IFERROR(VLOOKUP($A41,Enquiry!$A:$K,4,0),"-")) | D41: =IF($A41="","",IFERROR(VLOOKUP($A41,Enquiry!$A:$K,5,0),"-")) | K41: =IF(A41="","",IF(H41="Win","✅ Move to PO Workflow","⬜ Not Won Yet"))
B42: =IF($A42="","",IFERROR(VLOOKUP($A42,Enquiry!$A:$K,3,0),"-")) | C42: =IF($A42="","",IFERROR(VLOOKUP($A42,Enquiry!$A:$K,4,0),"-")) | D42: =IF($A42="","",IFERROR(VLOOKUP($A42,Enquiry!$A:$K,5,0),"-")) | K42: =IF(A42="","",IF(H42="Win","✅ Move to PO Workflow","⬜ Not Won Yet"))
B43: =IF($A43="","",IFERROR(VLOOKUP($A43,Enquiry!$A:$K,3,0),"-")) | C43: =IF($A43="","",IFERROR(VLOOKUP($A43,Enquiry!$A:$K,4,0),"-")) | D43: =IF($A43="","",IFERROR(VLOOKUP($A43,Enquiry!$A:$K,5,0),"-")) | K43: =IF(A43="","",IF(H43="Win","✅ Move to PO Workflow","⬜ Not Won Yet"))
B44: =IF($A44="","",IFERROR(VLOOKUP($A44,Enquiry!$A:$K,3,0),"-")) | C44: =IF($A44="","",IFERROR(VLOOKUP($A44,Enquiry!$A:$K,4,0),"-")) | D44: =IF($A44="","",IFERROR(VLOOKUP($A44,Enquiry!$A:$K,5,0),"-")) | K44: =IF(A44="","",IF(H44="Win","✅ Move to PO Workflow","⬜ Not Won Yet"))
... B502: =IF($A502="","",IFERROR(VLOOKUP($A502,Enquiry!$A:$K,3,0),"-")) | C502: =IF($A502="","",IFERROR(VLOOKUP($A502,Enquiry!$A:$K,4,0),"-")) | D502: =IF($A502="","",IFERROR(VLOOKUP($A502,Enquiry!$A:$K,5,0),"-")) | K502: =IF(A502="","",IF(H502="Win","✅ Move to PO Workflow","⬜ Not Won Yet"))

Sheet PO_Workflow
A1: 🔗 PO Workflow Bridge — Deal (Win) → PO Generation
A2: 💡 HOW TO USE: (1) Copy the Deal ID from the Deal sheet for any '✅ Win' deal. (2) Paste it into column A below. Fields auto-populate from CRM. (3) Manually fill the grey-shaded ops columns (PO Number, Dates, GST, Cadence). (4) Once complete, enter the PO Number into Input_PO to begin invoicing.
A3: Source Deal ID | B3: Deal Validation | C3: Customer Name | D3: Contact Name | E3: Service Category | F3: Service Description | G3: Deal Value (₹) | H3: Sales Owner | I3: Expected Close Date | J3: PO Number | K3: PO Date | L3: Start Date | M3: End Date | N3: Billing Terms | O3: Advance % | P3: GST Number | Q3: Notes
A4: 🟦 Teal = Auto-populated from CRM Deal sheet | I4: ⬜ Grey = Manual entry by Operations team
A5: L001 | B5: ✅ Win – Proceed | C5: CitiusCloud Services | D5: Roshan Shetty | E5: Consulting | F5: Growth Advisory | G5: 600000 | H5: Arunava Chakrabarty | I5: 45919 | J5: PO-00322 | K5: 45930 | L5: 45931 | M5: 46022 | N5: Monthly | O5: 0 | P5: 27AANFC2669L1ZV | Q5: Consulting for 3 months - Oct 25 to Dec 2
A6: L008 | B6: ✅ Win – Proceed | C6: TechMahindra Ltd | D6: Anil Sharma | E6: Consulting | F6: Growth Advisory | G6: 1100000 | H6: Praveen Sahai | I6: 45747 | J6: PO-00323 | K6: 45744 | L6: 45748 | M6: 46022 | N6: Monthly | O6: 10 | P6: 29AABCT1332L1ZV | Q6: TechMahindra consulting retainer 9M
A7: L009 | B7: ✅ Win – Proceed | C7: Wipro Technologies Ltd | D7: Sneha Kapoor | E7: Software Dev | F7: Agentic Tool | G7: 3800000 | H7: Asif Bhat | I7: 45777 | J7: PO-00324 | K7: 45772 | L7: 45778 | M7: 45961 | N7: Milestone | O7: 20 | P7: 29AAACW0867A1ZE | Q7: Wipro AI tool dev - 3 milestones
A8: L010 | B8: ✅ Win – Proceed | C8: Infosys BPM Ltd | D8: Rahul Menon | E8: Cybersecurity | F8: Cyber Security | G8: 800000 | H8: Dilip Sundaram | I8: 45792 | J8: PO-00325 | K8: 45787 | L8: 45792 | M8: 45884 | N8: Quarterly | O8: 0 | P8: 33AAAAI0015L1ZN | Q8: Infosys cybersec audit Q2-Q3
A9: L011 | B9: ✅ Win – Proceed | C9: HCL Technologies | D9: Priya Nair | E9: Marketing | F9: Brand Assets | G9: 2200000 | H9: Avinash | I9: 45838 | J9: PO-00326 | K9: 45836 | L9: 45839 | M9: 46022 | N9: Milestone | O9: 25 | P9: 27AAACM3025B1Z5 | Q9: HCL brand relaunch 4 phases
A10: L012 | B10: ✅ Win – Proceed | C10: Reliance Industries | D10: Amit Gupta | E10: Finance | F10: FinOps/Biz Ops | G10: 900000 | H10: Saji Mathew | I10: 45853 | J10: PO-00327 | K10: 45848 | L10: 45853 | M10: 46022 | N10: Monthly | O10: 0 | P10: 27AAACP1409L1ZV | Q10: Reliance FinOps monthly
A11: L013 | B11: ✅ Win – Proceed | C11: Tata Consultancy Services | D11: Deepa Iyer | E11: Software Dev | F11: CMS / CLM | G11: 2900000 | H11: Tarun Shiroley | I11: 45869 | J11: PO-00328 | K11: 45866 | L11: 45870 | M11: 46142 | N11: Monthly | O11: 10 | P11: 27AAACT3640Q1ZC | Q11: TCS CMS 9 month integration
A12: L014 | B12: ✅ Win – Proceed | C12: HDFC Bank Ltd | D12: Sanjay Pillai | E12: Marketing | F12: ICP & ABM | G12: 1600000 | H12: Avinash | I12: 45900 | J12: PO-00329 | K12: 45894 | L12: 45901 | M12: 46081 | N12: Monthly | O12: 0 | P12: 29AAACH2702H1ZW | Q12: HDFC ABM pilot 6 months
A13: L015 | B13: ✅ Win – Proceed | C13: Accenture Solutions Pvt Ltd | D13: Monica Verma | E13: PreSales | F13: Training | G13: 600000 | H13: Hemant Tathod | I13: 45930 | J13: PO-00330 | K13: 45925 | L13: 45931 | M13: 46022 | N13: Monthly | O13: 0 | P13: 27AABCA8099E1ZF | Q13: Accenture training 3M
A14: L016 | B14: ✅ Win – Proceed | C14: Bajaj Finserv Ltd | D14: Vijay Kulkarni | E14: Finance | F14: Bill Discounting | G14: 720000 | H14: Arunava Chakrabarty | I14: 45945 | J14: PO-00331 | K14: 45940 | L14: 45945 | M14: 46126 | N14: Monthly | O14: 0 | P14: 27AABCB5432N1ZA | Q14: Bajaj FinServ bill discounting
A15: L017 | B15: ✅ Win – Proceed | C15: Larsen & Toubro Infotech | D15: Ritesh Patel | E15: Consulting | F15: FinOps/Biz Ops | G15: 1400000 | H15: Praveen Sahai | I15: 45961 | J15: PO-00332 | K15: 45958 | L15: 45962 | M15: 46142 | N15: Monthly | O15: 15 | P15: 27AADFL2572M1ZR | Q15: L&T consulting ops project
A16: L019 | B16: ✅ Win – Proceed | C16: Capgemini India Pvt Ltd | D16: Srinivas Rao | E16: Software Dev | F16: Agentic Tool | G16: 2500000 | H16: Asif Bhat | I16: 45991 | J16: PO-00333 | K16: 45986 | L16: 45992 | M16: 46173 | N16: Milestone | O16: 20 | P16: 29AACCG0692L1ZN | Q16: Capgemini Agentic AI phase 1
... A26: L042 | B26: ✅ Win – Proceed | C26: Razorpay Software Pvt Ltd | D26: Dev Mishra | E26: Marketing | F26: ICP & ABM | G26: 600000 | H26: Saji Mathew | I26: 46142 | J26: PO-00343 | K26: 46087 | L26: 46113 | M26: 46203 | N26: Monthly | O26: 0 | P26: 29AABCJ7654K1ZC | Q26: Juspay cashflow tools Q2
B27: =IF(A27="","",IFERROR(IF(VLOOKUP(A27,Deal!$A:$K,8,0)="Win","✅ Win – Proceed","⚠ Stage: "&VLOOKUP(A27,Deal!$A:$K,8,0)),"❌ Deal ID Not Found")) | C27: =IF(A27="","",IFERROR(VLOOKUP(A27,Deal!$A:$K,2,0),"")) | D27: =IF(A27="","",IFERROR(VLOOKUP(A27,Deal!$A:$K,3,0),"")) | E27: =IF(A27="","",IFERROR(VLOOKUP(A27,Deal!$A:$K,4,0),"")) | F27: =IF(A27="","",IFERROR(VLOOKUP(A27,Enquiry!$A:$K,6,0),"— Enter manually")) | G27: =IF(A27="","",IFERROR(VLOOKUP(A27,Deal!$A:$K,6,0),0)) | H27: =IF(A27="","",IFERROR(VLOOKUP(A27,Deal!$A:$K,9,0),"")) | I27: =IF(A27="","",IFERROR(VLOOKUP(A27,Deal!$A:$K,7,0),""))
B28: =IF(A28="","",IFERROR(IF(VLOOKUP(A28,Deal!$A:$K,8,0)="Win","✅ Win – Proceed","⚠ Stage: "&VLOOKUP(A28,Deal!$A:$K,8,0)),"❌ Deal ID Not Found")) | C28: =IF(A28="","",IFERROR(VLOOKUP(A28,Deal!$A:$K,2,0),"")) | D28: =IF(A28="","",IFERROR(VLOOKUP(A28,Deal!$A:$K,3,0),"")) | E28: =IF(A28="","",IFERROR(VLOOKUP(A28,Deal!$A:$K,4,0),"")) | F28: =IF(A28="","",IFERROR(VLOOKUP(A28,Enquiry!$A:$K,6,0),"— Enter manually")) | G28: =IF(A28="","",IFERROR(VLOOKUP(A28,Deal!$A:$K,6,0),0)) | H28: =IF(A28="","",IFERROR(VLOOKUP(A28,Deal!$A:$K,9,0),"")) | I28: =IF(A28="","",IFERROR(VLOOKUP(A28,Deal!$A:$K,7,0),""))
B29: =IF(A29="","",IFERROR(IF(VLOOKUP(A29,Deal!$A:$K,8,0)="Win","✅ Win – Proceed","⚠ Stage: "&VLOOKUP(A29,Deal!$A:$K,8,0)),"❌ Deal ID Not Found")) | C29: =IF(A29="","",IFERROR(VLOOKUP(A29,Deal!$A:$K,2,0),"")) | D29: =IF(A29="","",IFERROR(VLOOKUP(A29,Deal!$A:$K,3,0),"")) | E29: =IF(A29="","",IFERROR(VLOOKUP(A29,Deal!$A:$K,4,0),"")) | F29: =IF(A29="","",IFERROR(VLOOKUP(A29,Enquiry!$A:$K,6,0),"— Enter manually")) | G29: =IF(A29="","",IFERROR(VLOOKUP(A29,Deal!$A:$K,6,0),0)) | H29: =IF(A29="","",IFERROR(VLOOKUP(A29,Deal!$A:$K,9,0),"")) | I29: =IF(A29="","",IFERROR(VLOOKUP(A29,Deal!$A:$K,7,0),""))
B30: =IF(A30="","",IFERROR(IF(VLOOKUP(A30,Deal!$A:$K,8,0)="Win","✅ Win – Proceed","⚠ Stage: "&VLOOKUP(A30,Deal!$A:$K,8,0)),"❌ Deal ID Not Found")) | C30: =IF(A30="","",IFERROR(VLOOKUP(A30,Deal!$A:$K,2,0),"")) | D30: =IF(A30="","",IFERROR(VLOOKUP(A30,Deal!$A:$K,3,0),"")) | E30: =IF(A30="","",IFERROR(VLOOKUP(A30,Deal!$A:$K,4,0),"")) | F30: =IF(A30="","",IFERROR(VLOOKUP(A30,Enquiry!$A:$K,6,0),"— Enter manually")) | G30: =IF(A30="","",IFERROR(VLOOKUP(A30,Deal!$A:$K,6,0),0)) | H30: =IF(A30="","",IFERROR(VLOOKUP(A30,Deal!$A:$K,9,0),"")) | I30: =IF(A30="","",IFERROR(VLOOKUP(A30,Deal!$A:$K,7,0),""))
B31: =IF(A31="","",IFERROR(IF(VLOOKUP(A31,Deal!$A:$K,8,0)="Win","✅ Win – Proceed","⚠ Stage: "&VLOOKUP(A31,Deal!$A:$K,8,0)),"❌ Deal ID Not Found")) | C31: =IF(A31="","",IFERROR(VLOOKUP(A31,Deal!$A:$K,2,0),"")) | D31: =IF(A31="","",IFERROR(VLOOKUP(A31,Deal!$A:$K,3,0),"")) | E31: =IF(A31="","",IFERROR(VLOOKUP(A31,Deal!$A:$K,4,0),"")) | F31: =IF(A31="","",IFERROR(VLOOKUP(A31,Enquiry!$A:$K,6,0),"— Enter manually")) | G31: =IF(A31="","",IFERROR(VLOOKUP(A31,Deal!$A:$K,6,0),0)) | H31: =IF(A31="","",IFERROR(VLOOKUP(A31,Deal!$A:$K,9,0),"")) | I31: =IF(A31="","",IFERROR(VLOOKUP(A31,Deal!$A:$K,7,0),""))
B32: =IF(A32="","",IFERROR(IF(VLOOKUP(A32,Deal!$A:$K,8,0)="Win","✅ Win – Proceed","⚠ Stage: "&VLOOKUP(A32,Deal!$A:$K,8,0)),"❌ Deal ID Not Found")) | C32: =IF(A32="","",IFERROR(VLOOKUP(A32,Deal!$A:$K,2,0),"")) | D32: =IF(A32="","",IFERROR(VLOOKUP(A32,Deal!$A:$K,3,0),"")) | E32: =IF(A32="","",IFERROR(VLOOKUP(A32,Deal!$A:$K,4,0),"")) | F32: =IF(A32="","",IFERROR(VLOOKUP(A32,Enquiry!$A:$K,6,0),"— Enter manually")) | G32: =IF(A32="","",IFERROR(VLOOKUP(A32,Deal!$A:$K,6,0),0)) | H32: =IF(A32="","",IFERROR(VLOOKUP(A32,Deal!$A:$K,9,0),"")) | I32: =IF(A32="","",IFERROR(VLOOKUP(A32,Deal!$A:$K,7,0),""))
B33: =IF(A33="","",IFERROR(IF(VLOOKUP(A33,Deal!$A:$K,8,0)="Win","✅ Win – Proceed","⚠ Stage: "&VLOOKUP(A33,Deal!$A:$K,8,0)),"❌ Deal ID Not Found")) | C33: =IF(A33="","",IFERROR(VLOOKUP(A33,Deal!$A:$K,2,0),"")) | D33: =IF(A33="","",IFERROR(VLOOKUP(A33,Deal!$A:$K,3,0),"")) | E33: =IF(A33="","",IFERROR(VLOOKUP(A33,Deal!$A:$K,4,0),"")) | F33: =IF(A33="","",IFERROR(VLOOKUP(A33,Enquiry!$A:$K,6,0),"— Enter manually")) | G33: =IF(A33="","",IFERROR(VLOOKUP(A33,Deal!$A:$K,6,0),0)) | H33: =IF(A33="","",IFERROR(VLOOKUP(A33,Deal!$A:$K,9,0),"")) | I33: =IF(A33="","",IFERROR(VLOOKUP(A33,Deal!$A:$K,7,0),""))
B34: =IF(A34="","",IFERROR(IF(VLOOKUP(A34,Deal!$A:$K,8,0)="Win","✅ Win – Proceed","⚠ Stage: "&VLOOKUP(A34,Deal!$A:$K,8,0)),"❌ Deal ID Not Found")) | C34: =IF(A34="","",IFERROR(VLOOKUP(A34,Deal!$A:$K,2,0),"")) | D34: =IF(A34="","",IFERROR(VLOOKUP(A34,Deal!$A:$K,3,0),"")) | E34: =IF(A34="","",IFERROR(VLOOKUP(A34,Deal!$A:$K,4,0),"")) | F34: =IF(A34="","",IFERROR(VLOOKUP(A34,Enquiry!$A:$K,6,0),"— Enter manually")) | G34: =IF(A34="","",IFERROR(VLOOKUP(A34,Deal!$A:$K,6,0),0)) | H34: =IF(A34="","",IFERROR(VLOOKUP(A34,Deal!$A:$K,9,0),"")) | I34: =IF(A34="","",IFERROR(VLOOKUP(A34,Deal!$A:$K,7,0),""))
B35: =IF(A35="","",IFERROR(IF(VLOOKUP(A35,Deal!$A:$K,8,0)="Win","✅ Win – Proceed","⚠ Stage: "&VLOOKUP(A35,Deal!$A:$K,8,0)),"❌ Deal ID Not Found")) | C35: =IF(A35="","",IFERROR(VLOOKUP(A35,Deal!$A:$K,2,0),"")) | D35: =IF(A35="","",IFERROR(VLOOKUP(A35,Deal!$A:$K,3,0),"")) | E35: =IF(A35="","",IFERROR(VLOOKUP(A35,Deal!$A:$K,4,0),"")) | F35: =IF(A35="","",IFERROR(VLOOKUP(A35,Enquiry!$A:$K,6,0),"— Enter manually")) | G35: =IF(A35="","",IFERROR(VLOOKUP(A35,Deal!$A:$K,6,0),0)) | H35: =IF(A35="","",IFERROR(VLOOKUP(A35,Deal!$A:$K,9,0),"")) | I35: =IF(A35="","",IFERROR(VLOOKUP(A35,Deal!$A:$K,7,0),""))
B36: =IF(A36="","",IFERROR(IF(VLOOKUP(A36,Deal!$A:$K,8,0)="Win","✅ Win – Proceed","⚠ Stage: "&VLOOKUP(A36,Deal!$A:$K,8,0)),"❌ Deal ID Not Found")) | C36: =IF(A36="","",IFERROR(VLOOKUP(A36,Deal!$A:$K,2,0),"")) | D36: =IF(A36="","",IFERROR(VLOOKUP(A36,Deal!$A:$K,3,0),"")) | E36: =IF(A36="","",IFERROR(VLOOKUP(A36,Deal!$A:$K,4,0),"")) | F36: =IF(A36="","",IFERROR(VLOOKUP(A36,Enquiry!$A:$K,6,0),"— Enter manually")) | G36: =IF(A36="","",IFERROR(VLOOKUP(A36,Deal!$A:$K,6,0),0)) | H36: =IF(A36="","",IFERROR(VLOOKUP(A36,Deal!$A:$K,9,0),"")) | I36: =IF(A36="","",IFERROR(VLOOKUP(A36,Deal!$A:$K,7,0),""))
B37: =IF(A37="","",IFERROR(IF(VLOOKUP(A37,Deal!$A:$K,8,0)="Win","✅ Win – Proceed","⚠ Stage: "&VLOOKUP(A37,Deal!$A:$K,8,0)),"❌ Deal ID Not Found")) | C37: =IF(A37="","",IFERROR(VLOOKUP(A37,Deal!$A:$K,2,0),"")) | D37: =IF(A37="","",IFERROR(VLOOKUP(A37,Deal!$A:$K,3,0),"")) | E37: =IF(A37="","",IFERROR(VLOOKUP(A37,Deal!$A:$K,4,0),"")) | F37: =IF(A37="","",IFERROR(VLOOKUP(A37,Enquiry!$A:$K,6,0),"— Enter manually")) | G37: =IF(A37="","",IFERROR(VLOOKUP(A37,Deal!$A:$K,6,0),0)) | H37: =IF(A37="","",IFERROR(VLOOKUP(A37,Deal!$A:$K,9,0),"")) | I37: =IF(A37="","",IFERROR(VLOOKUP(A37,Deal!$A:$K,7,0),""))
B38: =IF(A38="","",IFERROR(IF(VLOOKUP(A38,Deal!$A:$K,8,0)="Win","✅ Win – Proceed","⚠ Stage: "&VLOOKUP(A38,Deal!$A:$K,8,0)),"❌ Deal ID Not Found")) | C38: =IF(A38="","",IFERROR(VLOOKUP(A38,Deal!$A:$K,2,0),"")) | D38: =IF(A38="","",IFERROR(VLOOKUP(A38,Deal!$A:$K,3,0),"")) | E38: =IF(A38="","",IFERROR(VLOOKUP(A38,Deal!$A:$K,4,0),"")) | F38: =IF(A38="","",IFERROR(VLOOKUP(A38,Enquiry!$A:$K,6,0),"— Enter manually")) | G38: =IF(A38="","",IFERROR(VLOOKUP(A38,Deal!$A:$K,6,0),0)) | H38: =IF(A38="","",IFERROR(VLOOKUP(A38,Deal!$A:$K,9,0),"")) | I38: =IF(A38="","",IFERROR(VLOOKUP(A38,Deal!$A:$K,7,0),""))
... B203: =IF(A203="","",IFERROR(IF(VLOOKUP(A203,Deal!$A:$K,8,0)="Win","✅ Win – Proceed","⚠ Stage: "&VLOOKUP(A203,Deal!$A:$K,8,0)),"❌ Deal ID Not Found")) | C203: =IF(A203="","",IFERROR(VLOOKUP(A203,Deal!$A:$K,2,0),"")) | D203: =IF(A203="","",IFERROR(VLOOKUP(A203,Deal!$A:$K,3,0),"")) | E203: =IF(A203="","",IFERROR(VLOOKUP(A203,Deal!$A:$K,4,0),"")) | F203: =IF(A203="","",IFERROR(VLOOKUP(A203,Enquiry!$A:$K,6,0),"— Enter manually")) | G203: =IF(A203="","",IFERROR(VLOOKUP(A203,Deal!$A:$K,6,0),0)) | H203: =IF(A203="","",IFERROR(VLOOKUP(A203,Deal!$A:$K,9,0),"")) | I203: =IF(A203="","",IFERROR(VLOOKUP(A203,Deal!$A:$K,7,0),""))

Sheet Input_PO
A1: PO Status | B1: Validated (Yes/No) | C1: Source Deal ID ← Enter Here | D1: PO Number | E1: Customer Name | F1: Company | G1: GST Number | H1: Service Category | I1: Service Description | J1: PO Date | K1: Start Date | L1: End Date | M1: Duration (Months) | N1: Quantity | O1: Total PO Value | P1: PO Monthly Billing | Q1: Billing Terms | R1: Advance % | S1: Milestone Details | T1: Assigned Sales Owner | U1: Proposal Reference | V1: Validation Status
D2: 💡 HOW TO USE: Enter the Source Deal ID in column U (e.g. L001). Columns B–P auto-populate from PO_Workflow. Manually fill Quantity (K), Milestone Details (O), PO Status (S), and Validated (T). Blue text = auto-populated formula. Col A, J, R are also automatic.
A3: Completed | B3: Yes | C3: L001 | D3: PO-00322 | E3: CitiusCloud Services | F3: CitiusCloud Services | G3: 27AANFC2669L1ZV | H3: Consulting | I3: Growth Advisory | J3: 45930 | K3: 45931 | L3: 46022 | M3: 3 | N3: 3 | O3: 600000 | P3: 200000 | Q3: Monthly | R3: 0 | S3: Phase 1: Oct-Dec 2025 @ ₹2,00,000/month | T3: Arunava Chakrabarty | U3: Ref: L001 | V3: Validated
A4: Completed | B4: Yes | C4: L008 | D4: PO-00323 | E4: TechMahindra Ltd | F4: TechMahindra Ltd | G4: 29AABCT1332L1ZV | H4: Consulting | I4: Growth Advisory | J4: 45744 | K4: 45748 | L4: 46022 | M4: 9 | N4: 9 | O4: 1100000 | P4: 122222 | Q4: Monthly | R4: 10 | S4: Monthly: Apr-Dec 2025 @ ₹1,22,222/month | T4: Praveen Sahai | U4: Ref: L008 | V4: Validated
A5: Completed | B5: Yes | C5: L009 | D5: PO-00324 | E5: Wipro Technologies Ltd | F5: Wipro Technologies Ltd | G5: 29AAACW0867A1ZE | H5: Software Dev | I5: Agentic Tool | J5: 45772 | K5: 45778 | L5: 45961 | M5: 6 | N5: 3 | O5: 3800000 | P5: 633333 | Q5: Milestone | R5: 20 | S5: M1: Discovery ₹7,60,000 | M2: Dev ₹15,20,000 | M3: Delivery ₹15,20,000 | T5: Asif Bhat | U5: Ref: L009 | V5: Validated
A6: Completed | B6: Yes | C6: L010 | D6: PO-00325 | E6: Infosys BPM Ltd | F6: Infosys BPM Ltd | G6: 33AAAAI0015L1ZN | H6: Cybersecurity | I6: Cyber Security | J6: 45787 | K6: 45792 | L6: 45884 | M6: 4 | N6: 4 | O6: 800000 | P6: 200000 | Q6: Quarterly | R6: 0 | S6: Q1: ₹2,00,000 | Q2: ₹2,00,000 | Q3: ₹2,00,000 | Q4: ₹2,00,000 | T6: Dilip Sundaram | U6: Ref: L010 | V6: Validated
A7: Completed | B7: Yes | C7: L011 | D7: PO-00326 | E7: HCL Technologies | F7: HCL Technologies | G7: 27AAACM3025B1Z5 | H7: Marketing | I7: Brand Assets | J7: 45836 | K7: 45839 | L7: 46022 | M7: 6 | N7: 3 | O7: 2200000 | P7: 366667 | Q7: Milestone | R7: 25 | S7: M1: Concept ₹5,50,000 | M2: Design ₹5,50,000 | M3: Launch ₹11,00,000 | T7: Avinash | U7: Ref: L011 | V7: Validated
A8: Completed | B8: Yes | C8: L012 | D8: PO-00327 | E8: Reliance Industries | F8: Reliance Industries | G8: 27AAACP1409L1ZV | H8: Finance | I8: FinOps/Biz Ops | J8: 45848 | K8: 45853 | L8: 46022 | M8: 6 | N8: 6 | O8: 900000 | P8: 150000 | Q8: Monthly | R8: 0 | S8: Monthly: Jul-Dec 2025 @ ₹1,50,000/month | T8: Saji Mathew | U8: Ref: L012 | V8: Validated
A9: Active | B9: Yes | C9: L013 | D9: PO-00328 | E9: Tata Consultancy Services | F9: Tata Consultancy Services | G9: 27AAACT3640Q1ZC | H9: Software Dev | I9: CMS / CLM | J9: 45866 | K9: 45870 | L9: 46142 | M9: 9 | N9: 9 | O9: 2900000 | P9: 322222 | Q9: Monthly | R9: 10 | S9: Monthly: Aug 2025-Apr 2026 @ ₹3,22,222/month | T9: Tarun Shiroley | U9: Ref: L013 | V9: Validated
A10: Completed | B10: Yes | C10: L014 | D10: PO-00329 | E10: HDFC Bank Ltd | F10: HDFC Bank Ltd | G10: 29AAACH2702H1ZW | H10: Marketing | I10: ICP & ABM | J10: 45894 | K10: 45901 | L10: 46081 | M10: 6 | N10: 6 | O10: 1600000 | P10: 266667 | Q10: Monthly | R10: 0 | S10: Monthly: Sep 2025-Feb 2026 @ ₹2,66,667/month | T10: Avinash | U10: Ref: L014 | V10: Validated
A11: Completed | B11: Yes | C11: L015 | D11: PO-00330 | E11: Accenture Solutions Pvt Ltd | F11: Accenture Solutions Pvt Ltd | G11: 27AABCA8099E1ZF | H11: PreSales | I11: Training | J11: 45925 | K11: 45931 | L11: 46022 | M11: 3 | N11: 3 | O11: 600000 | P11: 200000 | Q11: Monthly | R11: 0 | S11: Monthly: Oct-Dec 2025 @ ₹2,00,000/month | T11: Hemant Tathod | U11: Ref: L015 | V11: Validated
A12: Active | B12: Yes | C12: L016 | D12: PO-00331 | E12: Bajaj Finserv Ltd | F12: Bajaj Finserv Ltd | G12: 27AABCB5432N1ZA | H12: Finance | I12: Bill Discounting | J12: 45940 | K12: 45945 | L12: 46126 | M12: 7 | N12: 7 | O12: 720000 | P12: 102857 | Q12: Monthly | R12: 0 | S12: Monthly: Oct 2025-Apr 2026 @ ₹1,02,857/month | T12: Arunava Chakrabarty | U12: Ref: L016 | V12: Validated
A13: Active | B13: Yes | C13: L017 | D13: PO-00332 | E13: Larsen & Toubro Infotech | F13: Larsen & Toubro Infotech | G13: 27AADFL2572M1ZR | H13: Consulting | I13: FinOps/Biz Ops | J13: 45958 | K13: 45962 | L13: 46142 | M13: 6 | N13: 6 | O13: 1400000 | P13: 233333 | Q13: Monthly | R13: 15 | S13: Monthly: Nov 2025-Apr 2026 @ ₹2,33,333/month | T13: Praveen Sahai | U13: Ref: L017 | V13: Validated
A14: Active | B14: Yes | C14: L019 | D14: PO-00333 | E14: Capgemini India Pvt Ltd | F14: Capgemini India Pvt Ltd | G14: 29AACCG0692L1ZN | H14: Software Dev | I14: Agentic Tool | J14: 45986 | K14: 45992 | L14: 46173 | M14: 6 | N14: 3 | O14: 2500000 | P14: 416667 | Q14: Milestone | R14: 20 | S14: M1: Onboarding ₹8,33,333 | M2: Integration ₹8,33,333 | M3: Delivery ₹8,33,334 | T14: Asif Bhat | U14: Ref: L019 | V14: Validated
... A24: Active | B24: Yes | C24: L042 | D24: PO-00343 | E24: Razorpay Software Pvt Ltd | F24: Razorpay Software Pvt Ltd | G24: 29AABCJ7654K1ZC | H24: Marketing | I24: ICP & ABM | J24: 46087 | K24: 46113 | L24: 46203 | M24: 3 | N24: 3 | O24: 600000 | P24: 200000 | Q24: Monthly | R24: 0 | S24: Monthly: Apr-Jun 2026 @ ₹2,00,000/month | T24: Saji Mathew | U24: Ref: L042 | V24: Validated
D25: =IF(C25<>"",IFERROR(VLOOKUP(C25,PO_Workflow!$A:$Q,10,0),""),IF(E25="","","PO-"&TEXT(ROW()-2,"0000"))) | E25: =IF(C25="","",IFERROR(VLOOKUP(C25,PO_Workflow!$A:$Q,3,0),"")) | F25: =IF(C25="","",IFERROR(VLOOKUP(C25,PO_Workflow!$A:$Q,3,0),"")) | G25: =IF(C25="","",IFERROR(VLOOKUP(C25,PO_Workflow!$A:$Q,16,0),"")) | H25: =IF(C25="","",IFERROR(VLOOKUP(C25,PO_Workflow!$A:$Q,5,0),"")) | I25: =IF(C25="","",IFERROR(VLOOKUP(C25,PO_Workflow!$A:$Q,6,0),"")) | J25: =IF(C25="","",IFERROR(VLOOKUP(C25,PO_Workflow!$A:$Q,11,0),"")) | K25: =IF(C25="","",IFERROR(VLOOKUP(C25,PO_Workflow!$A:$Q,12,0),"")) | L25: =IF(C25="","",IFERROR(VLOOKUP(C25,PO_Workflow!$A:$Q,13,0),"")) | M25: =IF(OR(K25="",L25=""),"",((YEAR(L25)-YEAR(K25))*12)+MONTH(L25)-MONTH(K25)+1) | O25: =IF(C25="","",IFERROR(VLOOKUP(C25,PO_Workflow!$A:$Q,7,0),"")) | Q25: =IF(C25="","",IFERROR(VLOOKUP(C25,PO_Workflow!$A:$Q,14,0),"")) | R25: =IF(C25="","",IFERROR(VLOOKUP(C25,PO_Workflow!$A:$Q,15,0),"")) | T25: =IF(C25="","",IFERROR(VLOOKUP(C25,PO_Workflow!$A:$Q,8,0),"")) | U25: =IF(C25="","","Ref: "&C25) | V25: =IF(AND(C25="",E25=""),"",IF(OR(F25="",G25="",H25="",O25="",Q25=""),"Pending Validation",IF(AND(F25<>"",G25<>"",O25>0),"Validated","Mismatch")))
D26: =IF(C26<>"",IFERROR(VLOOKUP(C26,PO_Workflow!$A:$Q,10,0),""),IF(E26="","","PO-"&TEXT(ROW()-2,"0000"))) | E26: =IF(C26="","",IFERROR(VLOOKUP(C26,PO_Workflow!$A:$Q,3,0),"")) | F26: =IF(C26="","",IFERROR(VLOOKUP(C26,PO_Workflow!$A:$Q,3,0),"")) | G26: =IF(C26="","",IFERROR(VLOOKUP(C26,PO_Workflow!$A:$Q,16,0),"")) | H26: =IF(C26="","",IFERROR(VLOOKUP(C26,PO_Workflow!$A:$Q,5,0),"")) | I26: =IF(C26="","",IFERROR(VLOOKUP(C26,PO_Workflow!$A:$Q,6,0),"")) | J26: =IF(C26="","",IFERROR(VLOOKUP(C26,PO_Workflow!$A:$Q,11,0),"")) | K26: =IF(C26="","",IFERROR(VLOOKUP(C26,PO_Workflow!$A:$Q,12,0),"")) | L26: =IF(C26="","",IFERROR(VLOOKUP(C26,PO_Workflow!$A:$Q,13,0),"")) | M26: =IF(OR(K26="",L26=""),"",((YEAR(L26)-YEAR(K26))*12)+MONTH(L26)-MONTH(K26)+1) | O26: =IF(C26="","",IFERROR(VLOOKUP(C26,PO_Workflow!$A:$Q,7,0),"")) | Q26: =IF(C26="","",IFERROR(VLOOKUP(C26,PO_Workflow!$A:$Q,14,0),"")) | R26: =IF(C26="","",IFERROR(VLOOKUP(C26,PO_Workflow!$A:$Q,15,0),"")) | T26: =IF(C26="","",IFERROR(VLOOKUP(C26,PO_Workflow!$A:$Q,8,0),"")) | U26: =IF(C26="","","Ref: "&C26) | V26: =IF(AND(C26="",E26=""),"",IF(OR(F26="",G26="",H26="",O26="",Q26=""),"Pending Validation",IF(AND(F26<>"",G26<>"",O26>0),"Validated","Mismatch")))
D27: =IF(C27<>"",IFERROR(VLOOKUP(C27,PO_Workflow!$A:$Q,10,0),""),IF(E27="","","PO-"&TEXT(ROW()-2,"0000"))) | E27: =IF(C27="","",IFERROR(VLOOKUP(C27,PO_Workflow!$A:$Q,3,0),"")) | F27: =IF(C27="","",IFERROR(VLOOKUP(C27,PO_Workflow!$A:$Q,3,0),"")) | G27: =IF(C27="","",IFERROR(VLOOKUP(C27,PO_Workflow!$A:$Q,16,0),"")) | H27: =IF(C27="","",IFERROR(VLOOKUP(C27,PO_Workflow!$A:$Q,5,0),"")) | I27: =IF(C27="","",IFERROR(VLOOKUP(C27,PO_Workflow!$A:$Q,6,0),"")) | J27: =IF(C27="","",IFERROR(VLOOKUP(C27,PO_Workflow!$A:$Q,11,0),"")) | K27: =IF(C27="","",IFERROR(VLOOKUP(C27,PO_Workflow!$A:$Q,12,0),"")) | L27: =IF(C27="","",IFERROR(VLOOKUP(C27,PO_Workflow!$A:$Q,13,0),"")) | M27: =IF(OR(K27="",L27=""),"",((YEAR(L27)-YEAR(K27))*12)+MONTH(L27)-MONTH(K27)+1) | O27: =IF(C27="","",IFERROR(VLOOKUP(C27,PO_Workflow!$A:$Q,7,0),"")) | Q27: =IF(C27="","",IFERROR(VLOOKUP(C27,PO_Workflow!$A:$Q,14,0),"")) | R27: =IF(C27="","",IFERROR(VLOOKUP(C27,PO_Workflow!$A:$Q,15,0),"")) | T27: =IF(C27="","",IFERROR(VLOOKUP(C27,PO_Workflow!$A:$Q,8,0),"")) | U27: =IF(C27="","","Ref: "&C27) | V27: =IF(AND(C27="",E27=""),"",IF(OR(F27="",G27="",H27="",O27="",Q27=""),"Pending Validation",IF(AND(F27<>"",G27<>"",O27>0),"Validated","Mismatch")))
D28: =IF(C28<>"",IFERROR(VLOOKUP(C28,PO_Workflow!$A:$Q,10,0),""),IF(E28="","","PO-"&TEXT(ROW()-2,"0000"))) | E28: =IF(C28="","",IFERROR(VLOOKUP(C28,PO_Workflow!$A:$Q,3,0),"")) | F28: =IF(C28="","",IFERROR(VLOOKUP(C28,PO_Workflow!$A:$Q,3,0),"")) | G28: =IF(C28="","",IFERROR(VLOOKUP(C28,PO_Workflow!$A:$Q,16,0),"")) | H28: =IF(C28="","",IFERROR(VLOOKUP(C28,PO_Workflow!$A:$Q,5,0),"")) | I28: =IF(C28="","",IFERROR(VLOOKUP(C28,PO_Workflow!$A:$Q,6,0),"")) | J28: =IF(C28="","",IFERROR(VLOOKUP(C28,PO_Workflow!$A:$Q,11,0),"")) | K28: =IF(C28="","",IFERROR(VLOOKUP(C28,PO_Workflow!$A:$Q,12,0),"")) | L28: =IF(C28="","",IFERROR(VLOOKUP(C28,PO_Workflow!$A:$Q,13,0),"")) | M28: =IF(OR(K28="",L28=""),"",((YEAR(L28)-YEAR(K28))*12)+MONTH(L28)-MONTH(K28)+1) | O28: =IF(C28="","",IFERROR(VLOOKUP(C28,PO_Workflow!$A:$Q,7,0),"")) | Q28: =IF(C28="","",IFERROR(VLOOKUP(C28,PO_Workflow!$A:$Q,14,0),"")) | R28: =IF(C28="","",IFERROR(VLOOKUP(C28,PO_Workflow!$A:$Q,15,0),"")) | T28: =IF(C28="","",IFERROR(VLOOKUP(C28,PO_Workflow!$A:$Q,8,0),"")) | U28: =IF(C28="","","Ref: "&C28) | V28: =IF(AND(C28="",E28=""),"",IF(OR(F28="",G28="",H28="",O28="",Q28=""),"Pending Validation",IF(AND(F28<>"",G28<>"",O28>0),"Validated","Mismatch")))
D29: =IF(C29<>"",IFERROR(VLOOKUP(C29,PO_Workflow!$A:$Q,10,0),""),IF(E29="","","PO-"&TEXT(ROW()-2,"0000"))) | E29: =IF(C29="","",IFERROR(VLOOKUP(C29,PO_Workflow!$A:$Q,3,0),"")) | F29: =IF(C29="","",IFERROR(VLOOKUP(C29,PO_Workflow!$A:$Q,3,0),"")) | G29: =IF(C29="","",IFERROR(VLOOKUP(C29,PO_Workflow!$A:$Q,16,0),"")) | H29: =IF(C29="","",IFERROR(VLOOKUP(C29,PO_Workflow!$A:$Q,5,0),"")) | I29: =IF(C29="","",IFERROR(VLOOKUP(C29,PO_Workflow!$A:$Q,6,0),"")) | J29: =IF(C29="","",IFERROR(VLOOKUP(C29,PO_Workflow!$A:$Q,11,0),"")) | K29: =IF(C29="","",IFERROR(VLOOKUP(C29,PO_Workflow!$A:$Q,12,0),"")) | L29: =IF(C29="","",IFERROR(VLOOKUP(C29,PO_Workflow!$A:$Q,13,0),"")) | M29: =IF(OR(K29="",L29=""),"",((YEAR(L29)-YEAR(K29))*12)+MONTH(L29)-MONTH(K29)+1) | O29: =IF(C29="","",IFERROR(VLOOKUP(C29,PO_Workflow!$A:$Q,7,0),"")) | Q29: =IF(C29="","",IFERROR(VLOOKUP(C29,PO_Workflow!$A:$Q,14,0),"")) | R29: =IF(C29="","",IFERROR(VLOOKUP(C29,PO_Workflow!$A:$Q,15,0),"")) | T29: =IF(C29="","",IFERROR(VLOOKUP(C29,PO_Workflow!$A:$Q,8,0),"")) | U29: =IF(C29="","","Ref: "&C29) | V29: =IF(AND(C29="",E29=""),"",IF(OR(F29="",G29="",H29="",O29="",Q29=""),"Pending Validation",IF(AND(F29<>"",G29<>"",O29>0),"Validated","Mismatch")))
D30: =IF(C30<>"",IFERROR(VLOOKUP(C30,PO_Workflow!$A:$Q,10,0),""),IF(E30="","","PO-"&TEXT(ROW()-2,"0000"))) | E30: =IF(C30="","",IFERROR(VLOOKUP(C30,PO_Workflow!$A:$Q,3,0),"")) | F30: =IF(C30="","",IFERROR(VLOOKUP(C30,PO_Workflow!$A:$Q,3,0),"")) | G30: =IF(C30="","",IFERROR(VLOOKUP(C30,PO_Workflow!$A:$Q,16,0),"")) | H30: =IF(C30="","",IFERROR(VLOOKUP(C30,PO_Workflow!$A:$Q,5,0),"")) | I30: =IF(C30="","",IFERROR(VLOOKUP(C30,PO_Workflow!$A:$Q,6,0),"")) | J30: =IF(C30="","",IFERROR(VLOOKUP(C30,PO_Workflow!$A:$Q,11,0),"")) | K30: =IF(C30="","",IFERROR(VLOOKUP(C30,PO_Workflow!$A:$Q,12,0),"")) | L30: =IF(C30="","",IFERROR(VLOOKUP(C30,PO_Workflow!$A:$Q,13,0),"")) | M30: =IF(OR(K30="",L30=""),"",((YEAR(L30)-YEAR(K30))*12)+MONTH(L30)-MONTH(K30)+1) | O30: =IF(C30="","",IFERROR(VLOOKUP(C30,PO_Workflow!$A:$Q,7,0),"")) | Q30: =IF(C30="","",IFERROR(VLOOKUP(C30,PO_Workflow!$A:$Q,14,0),"")) | R30: =IF(C30="","",IFERROR(VLOOKUP(C30,PO_Workflow!$A:$Q,15,0),"")) | T30: =IF(C30="","",IFERROR(VLOOKUP(C30,PO_Workflow!$A:$Q,8,0),"")) | U30: =IF(C30="","","Ref: "&C30) | V30: =IF(AND(C30="",E30=""),"",IF(OR(F30="",G30="",H30="",O30="",Q30=""),"Pending Validation",IF(AND(F30<>"",G30<>"",O30>0),"Validated","Mismatch")))
D31: =IF(C31<>"",IFERROR(VLOOKUP(C31,PO_Workflow!$A:$Q,10,0),""),IF(E31="","","PO-"&TEXT(ROW()-2,"0000"))) | E31: =IF(C31="","",IFERROR(VLOOKUP(C31,PO_Workflow!$A:$Q,3,0),"")) | F31: =IF(C31="","",IFERROR(VLOOKUP(C31,PO_Workflow!$A:$Q,3,0),"")) | G31: =IF(C31="","",IFERROR(VLOOKUP(C31,PO_Workflow!$A:$Q,16,0),"")) | H31: =IF(C31="","",IFERROR(VLOOKUP(C31,PO_Workflow!$A:$Q,5,0),"")) | I31: =IF(C31="","",IFERROR(VLOOKUP(C31,PO_Workflow!$A:$Q,6,0),"")) | J31: =IF(C31="","",IFERROR(VLOOKUP(C31,PO_Workflow!$A:$Q,11,0),"")) | K31: =IF(C31="","",IFERROR(VLOOKUP(C31,PO_Workflow!$A:$Q,12,0),"")) | L31: =IF(C31="","",IFERROR(VLOOKUP(C31,PO_Workflow!$A:$Q,13,0),"")) | M31: =IF(OR(K31="",L31=""),"",((YEAR(L31)-YEAR(K31))*12)+MONTH(L31)-MONTH(K31)+1) | O31: =IF(C31="","",IFERROR(VLOOKUP(C31,PO_Workflow!$A:$Q,7,0),"")) | Q31: =IF(C31="","",IFERROR(VLOOKUP(C31,PO_Workflow!$A:$Q,14,0),"")) | R31: =IF(C31="","",IFERROR(VLOOKUP(C31,PO_Workflow!$A:$Q,15,0),"")) | T31: =IF(C31="","",IFERROR(VLOOKUP(C31,PO_Workflow!$A:$Q,8,0),"")) | U31: =IF(C31="","","Ref: "&C31) | V31: =IF(AND(C31="",E31=""),"",IF(OR(F31="",G31="",H31="",O31="",Q31=""),"Pending Validation",IF(AND(F31<>"",G31<>"",O31>0),"Validated","Mismatch")))
D32: =IF(C32<>"",IFERROR(VLOOKUP(C32,PO_Workflow!$A:$Q,10,0),""),IF(E32="","","PO-"&TEXT(ROW()-2,"0000"))) | E32: =IF(C32="","",IFERROR(VLOOKUP(C32,PO_Workflow!$A:$Q,3,0),"")) | F32: =IF(C32="","",IFERROR(VLOOKUP(C32,PO_Workflow!$A:$Q,3,0),"")) | G32: =IF(C32="","",IFERROR(VLOOKUP(C32,PO_Workflow!$A:$Q,16,0),"")) | H32: =IF(C32="","",IFERROR(VLOOKUP(C32,PO_Workflow!$A:$Q,5,0),"")) | I32: =IF(C32="","",IFERROR(VLOOKUP(C32,PO_Workflow!$A:$Q,6,0),"")) | J32: =IF(C32="","",IFERROR(VLOOKUP(C32,PO_Workflow!$A:$Q,11,0),"")) | K32: =IF(C32="","",IFERROR(VLOOKUP(C32,PO_Workflow!$A:$Q,12,0),"")) | L32: =IF(C32="","",IFERROR(VLOOKUP(C32,PO_Workflow!$A:$Q,13,0),"")) | M32: =IF(OR(K32="",L32=""),"",((YEAR(L32)-YEAR(K32))*12)+MONTH(L32)-MONTH(K32)+1) | O32: =IF(C32="","",IFERROR(VLOOKUP(C32,PO_Workflow!$A:$Q,7,0),"")) | Q32: =IF(C32="","",IFERROR(VLOOKUP(C32,PO_Workflow!$A:$Q,14,0),"")) | R32: =IF(C32="","",IFERROR(VLOOKUP(C32,PO_Workflow!$A:$Q,15,0),"")) | T32: =IF(C32="","",IFERROR(VLOOKUP(C32,PO_Workflow!$A:$Q,8,0),"")) | U32: =IF(C32="","","Ref: "&C32) | V32: =IF(AND(C32="",E32=""),"",IF(OR(F32="",G32="",H32="",O32="",Q32=""),"Pending Validation",IF(AND(F32<>"",G32<>"",O32>0),"Validated","Mismatch")))
D33: =IF(C33<>"",IFERROR(VLOOKUP(C33,PO_Workflow!$A:$Q,10,0),""),IF(E33="","","PO-"&TEXT(ROW()-2,"0000"))) | E33: =IF(C33="","",IFERROR(VLOOKUP(C33,PO_Workflow!$A:$Q,3,0),"")) | F33: =IF(C33="","",IFERROR(VLOOKUP(C33,PO_Workflow!$A:$Q,3,0),"")) | G33: =IF(C33="","",IFERROR(VLOOKUP(C33,PO_Workflow!$A:$Q,16,0),"")) | H33: =IF(C33="","",IFERROR(VLOOKUP(C33,PO_Workflow!$A:$Q,5,0),"")) | I33: =IF(C33="","",IFERROR(VLOOKUP(C33,PO_Workflow!$A:$Q,6,0),"")) | J33: =IF(C33="","",IFERROR(VLOOKUP(C33,PO_Workflow!$A:$Q,11,0),"")) | K33: =IF(C33="","",IFERROR(VLOOKUP(C33,PO_Workflow!$A:$Q,12,0),"")) | L33: =IF(C33="","",IFERROR(VLOOKUP(C33,PO_Workflow!$A:$Q,13,0),"")) | M33: =IF(OR(K33="",L33=""),"",((YEAR(L33)-YEAR(K33))*12)+MONTH(L33)-MONTH(K33)+1) | O33: =IF(C33="","",IFERROR(VLOOKUP(C33,PO_Workflow!$A:$Q,7,0),"")) | Q33: =IF(C33="","",IFERROR(VLOOKUP(C33,PO_Workflow!$A:$Q,14,0),"")) | R33: =IF(C33="","",IFERROR(VLOOKUP(C33,PO_Workflow!$A:$Q,15,0),"")) | T33: =IF(C33="","",IFERROR(VLOOKUP(C33,PO_Workflow!$A:$Q,8,0),"")) | U33: =IF(C33="","","Ref: "&C33) | V33: =IF(AND(C33="",E33=""),"",IF(OR(F33="",G33="",H33="",O33="",Q33=""),"Pending Validation",IF(AND(F33<>"",G33<>"",O33>0),"Validated","Mismatch")))
D34: =IF(C34<>"",IFERROR(VLOOKUP(C34,PO_Workflow!$A:$Q,10,0),""),IF(E34="","","PO-"&TEXT(ROW()-2,"0000"))) | E34: =IF(C34="","",IFERROR(VLOOKUP(C34,PO_Workflow!$A:$Q,3,0),"")) | F34: =IF(C34="","",IFERROR(VLOOKUP(C34,PO_Workflow!$A:$Q,3,0),"")) | G34: =IF(C34="","",IFERROR(VLOOKUP(C34,PO_Workflow!$A:$Q,16,0),"")) | H34: =IF(C34="","",IFERROR(VLOOKUP(C34,PO_Workflow!$A:$Q,5,0),"")) | I34: =IF(C34="","",IFERROR(VLOOKUP(C34,PO_Workflow!$A:$Q,6,0),"")) | J34: =IF(C34="","",IFERROR(VLOOKUP(C34,PO_Workflow!$A:$Q,11,0),"")) | K34: =IF(C34="","",IFERROR(VLOOKUP(C34,PO_Workflow!$A:$Q,12,0),"")) | L34: =IF(C34="","",IFERROR(VLOOKUP(C34,PO_Workflow!$A:$Q,13,0),"")) | M34: =IF(OR(K34="",L34=""),"",((YEAR(L34)-YEAR(K34))*12)+MONTH(L34)-MONTH(K34)+1) | O34: =IF(C34="","",IFERROR(VLOOKUP(C34,PO_Workflow!$A:$Q,7,0),"")) | Q34: =IF(C34="","",IFERROR(VLOOKUP(C34,PO_Workflow!$A:$Q,14,0),"")) | R34: =IF(C34="","",IFERROR(VLOOKUP(C34,PO_Workflow!$A:$Q,15,0),"")) | T34: =IF(C34="","",IFERROR(VLOOKUP(C34,PO_Workflow!$A:$Q,8,0),"")) | U34: =IF(C34="","","Ref: "&C34) | V34: =IF(AND(C34="",E34=""),"",IF(OR(F34="",G34="",H34="",O34="",Q34=""),"Pending Validation",IF(AND(F34<>"",G34<>"",O34>0),"Validated","Mismatch")))
D35: =IF(C35<>"",IFERROR(VLOOKUP(C35,PO_Workflow!$A:$Q,10,0),""),IF(E35="","","PO-"&TEXT(ROW()-2,"0000"))) | E35: =IF(C35="","",IFERROR(VLOOKUP(C35,PO_Workflow!$A:$Q,3,0),"")) | F35: =IF(C35="","",IFERROR(VLOOKUP(C35,PO_Workflow!$A:$Q,3,0),"")) | G35: =IF(C35="","",IFERROR(VLOOKUP(C35,PO_Workflow!$A:$Q,16,0),"")) | H35: =IF(C35="","",IFERROR(VLOOKUP(C35,PO_Workflow!$A:$Q,5,0),"")) | I35: =IF(C35="","",IFERROR(VLOOKUP(C35,PO_Workflow!$A:$Q,6,0),"")) | J35: =IF(C35="","",IFERROR(VLOOKUP(C35,PO_Workflow!$A:$Q,11,0),"")) | K35: =IF(C35="","",IFERROR(VLOOKUP(C35,PO_Workflow!$A:$Q,12,0),"")) | L35: =IF(C35="","",IFERROR(VLOOKUP(C35,PO_Workflow!$A:$Q,13,0),"")) | M35: =IF(OR(K35="",L35=""),"",((YEAR(L35)-YEAR(K35))*12)+MONTH(L35)-MONTH(K35)+1) | O35: =IF(C35="","",IFERROR(VLOOKUP(C35,PO_Workflow!$A:$Q,7,0),"")) | Q35: =IF(C35="","",IFERROR(VLOOKUP(C35,PO_Workflow!$A:$Q,14,0),"")) | R35: =IF(C35="","",IFERROR(VLOOKUP(C35,PO_Workflow!$A:$Q,15,0),"")) | T35: =IF(C35="","",IFERROR(VLOOKUP(C35,PO_Workflow!$A:$Q,8,0),"")) | U35: =IF(C35="","","Ref: "&C35) | V35: =IF(AND(C35="",E35=""),"",IF(OR(F35="",G35="",H35="",O35="",Q35=""),"Pending Validation",IF(AND(F35<>"",G35<>"",O35>0),"Validated","Mismatch")))
D36: =IF(C36<>"",IFERROR(VLOOKUP(C36,PO_Workflow!$A:$Q,10,0),""),IF(E36="","","PO-"&TEXT(ROW()-2,"0000"))) | E36: =IF(C36="","",IFERROR(VLOOKUP(C36,PO_Workflow!$A:$Q,3,0),"")) | F36: =IF(C36="","",IFERROR(VLOOKUP(C36,PO_Workflow!$A:$Q,3,0),"")) | G36: =IF(C36="","",IFERROR(VLOOKUP(C36,PO_Workflow!$A:$Q,16,0),"")) | H36: =IF(C36="","",IFERROR(VLOOKUP(C36,PO_Workflow!$A:$Q,5,0),"")) | I36: =IF(C36="","",IFERROR(VLOOKUP(C36,PO_Workflow!$A:$Q,6,0),"")) | J36: =IF(C36="","",IFERROR(VLOOKUP(C36,PO_Workflow!$A:$Q,11,0),"")) | K36: =IF(C36="","",IFERROR(VLOOKUP(C36,PO_Workflow!$A:$Q,12,0),"")) | L36: =IF(C36="","",IFERROR(VLOOKUP(C36,PO_Workflow!$A:$Q,13,0),"")) | M36: =IF(OR(K36="",L36=""),"",((YEAR(L36)-YEAR(K36))*12)+MONTH(L36)-MONTH(K36)+1) | O36: =IF(C36="","",IFERROR(VLOOKUP(C36,PO_Workflow!$A:$Q,7,0),"")) | Q36: =IF(C36="","",IFERROR(VLOOKUP(C36,PO_Workflow!$A:$Q,14,0),"")) | R36: =IF(C36="","",IFERROR(VLOOKUP(C36,PO_Workflow!$A:$Q,15,0),"")) | T36: =IF(C36="","",IFERROR(VLOOKUP(C36,PO_Workflow!$A:$Q,8,0),"")) | U36: =IF(C36="","","Ref: "&C36) | V36: =IF(AND(C36="",E36=""),"",IF(OR(F36="",G36="",H36="",O36="",Q36=""),"Pending Validation",IF(AND(F36<>"",G36<>"",O36>0),"Validated","Mismatch")))
... D301: =IF(C301<>"",IFERROR(VLOOKUP(C301,PO_Workflow!$A:$Q,10,0),""),IF(E301="","","PO-"&TEXT(ROW()-2,"0000"))) | E301: =IF(C301="","",IFERROR(VLOOKUP(C301,PO_Workflow!$A:$Q,3,0),"")) | F301: =IF(C301="","",IFERROR(VLOOKUP(C301,PO_Workflow!$A:$Q,3,0),"")) | G301: =IF(C301="","",IFERROR(VLOOKUP(C301,PO_Workflow!$A:$Q,16,0),"")) | H301: =IF(C301="","",IFERROR(VLOOKUP(C301,PO_Workflow!$A:$Q,5,0),"")) | I301: =IF(C301="","",IFERROR(VLOOKUP(C301,PO_Workflow!$A:$Q,6,0),"")) | J301: =IF(C301="","",IFERROR(VLOOKUP(C301,PO_Workflow!$A:$Q,11,0),"")) | K301: =IF(C301="","",IFERROR(VLOOKUP(C301,PO_Workflow!$A:$Q,12,0),"")) | L301: =IF(C301="","",IFERROR(VLOOKUP(C301,PO_Workflow!$A:$Q,13,0),"")) | M301: =IF(OR(K301="",L301=""),"",((YEAR(L301)-YEAR(K301))*12)+MONTH(L301)-MONTH(K301)+1) | O301: =IF(C301="","",IFERROR(VLOOKUP(C301,PO_Workflow!$A:$Q,7,0),"")) | Q301: =IF(C301="","",IFERROR(VLOOKUP(C301,PO_Workflow!$A:$Q,14,0),"")) | R301: =IF(C301="","",IFERROR(VLOOKUP(C301,PO_Workflow!$A:$Q,15,0),"")) | T301: =IF(C301="","",IFERROR(VLOOKUP(C301,PO_Workflow!$A:$Q,8,0),"")) | U301: =IF(C301="","","Ref: "&C301) | V301: =IF(AND(C301="",E301=""),"",IF(OR(F301="",G301="",H301="",O301="",Q301=""),"Pending Validation",IF(AND(F301<>"",G301<>"",O301>0),"Validated","Mismatch")))

Sheet Contact
A1: Company Name | B1: Contact Name | C1: Email | D1: Phone | E1: City | F1: State | G1: Created Date
A2: 💡 All blue/teal columns auto-populate from Enquiry sheet. Only fill in Email (H), Phone (I), City (J), State (K) manually. Orange headers = manual entry required.
A3: CitiusCloud Services | B3: Roshan Shetty | C3: roshan.shetty@citiuscloud.com | D3: +91-9845001001 | E3: Bengaluru | F3: Karnataka | G3: 45891
A4: Galaxy Office Automation Pvt Ltd | B4: Anoop PaiDhungat | C4: anoop.paidhungat@galaxyoa.com | D4: +91-9845002002 | E4: Mumbai | F4: Maharashtra | G4: 45892
A5: Nutanix India Pvt Ltd | B5: Renu Asrani | C5: renu.asrani@nutanix.com | D5: +91-9845003003 | E5: Bengaluru | F5: Karnataka | G5: 45893
A6: ARCA Alternatives | B6: Sagar Nagaraj | C6: sagar.nagaraj@arcaalternatives.com | D6: +91-9845004004 | E6: Mumbai | F6: Maharashtra | G6: 45894
A7: Azentio | B7: Vamsi Chaitanya | C7: vamsi.chaitanya@azentio.com | D7: +91-9845005005 | E7: Bengaluru | F7: Karnataka | G7: 45894
A8: Checkpoint Software | B8: Keely Wilkins | C8: keely.wilkins@checkpoint.com | D8: +91-9845006006 | E8: Bengaluru | F8: Karnataka | G8: 45894
A9: Galaxy Office Automation Pvt Ltd | B9: Grishma Potdar | C9: anoop.paidhungat@galaxyoa.com | D9: +91-9845002002 | E9: Mumbai | F9: Maharashtra | G9: 45894
A10: TechMahindra Ltd | B10: Anil Sharma | C10: anil.sharma@techmahindra.com | D10: +91-9876501001 | E10: Mumbai | F10: Maharashtra | G10: 45667
A11: Wipro Technologies Ltd | B11: Sneha Kapoor | C11: sneha.kapoor@wipro.com | D11: +91-9876502002 | E11: Bengaluru | F11: Karnataka | G11: 45675
A12: Infosys BPM Ltd | B12: Rahul Menon | C12: rahul.menon@infosys.com | D12: +91-9876503003 | E12: Bengaluru | F12: Karnataka | G12: 45693
A13: HCL Technologies | B13: Priya Nair | C13: priya.nair@hcltech.com | D13: +91-9876504004 | E13: Noida | F13: Uttar Pradesh | G13: 45702
A14: Reliance Industries | B14: Amit Gupta | C14: amit.gupta@ril.com | D14: +91-9876505005 | E14: Mumbai | F14: Maharashtra | G14: 45718
... A49: Fashnear Technologies Pvt Ltd | B49: Preet Shah | C49: preet.shah@meesho.com | D49: +91-9876540040 | E49: Bengaluru | F49: Karnataka | G49: 46087
A50: Fashnear Technologies Pvt Ltd | B50: Preet Shah | G50: 46087
A51: =IF(Enquiry!B51="","",IFERROR(Enquiry!C51,"")) | B51: =IF(Enquiry!B51="","",IFERROR(Enquiry!D51,"")) | G51: =IF(Enquiry!B51="","",IFERROR(Enquiry!K51,""))
A52: =IF(Enquiry!B52="","",IFERROR(Enquiry!C52,"")) | B52: =IF(Enquiry!B52="","",IFERROR(Enquiry!D52,"")) | G52: =IF(Enquiry!B52="","",IFERROR(Enquiry!K52,""))
A53: =IF(Enquiry!B53="","",IFERROR(Enquiry!C53,"")) | B53: =IF(Enquiry!B53="","",IFERROR(Enquiry!D53,"")) | G53: =IF(Enquiry!B53="","",IFERROR(Enquiry!K53,""))
A54: =IF(Enquiry!B54="","",IFERROR(Enquiry!C54,"")) | B54: =IF(Enquiry!B54="","",IFERROR(Enquiry!D54,"")) | G54: =IF(Enquiry!B54="","",IFERROR(Enquiry!K54,""))
A55: =IF(Enquiry!B55="","",IFERROR(Enquiry!C55,"")) | B55: =IF(Enquiry!B55="","",IFERROR(Enquiry!D55,"")) | G55: =IF(Enquiry!B55="","",IFERROR(Enquiry!K55,""))
A56: =IF(Enquiry!B56="","",IFERROR(Enquiry!C56,"")) | B56: =IF(Enquiry!B56="","",IFERROR(Enquiry!D56,"")) | G56: =IF(Enquiry!B56="","",IFERROR(Enquiry!K56,""))
A57: =IF(Enquiry!B57="","",IFERROR(Enquiry!C57,"")) | B57: =IF(Enquiry!B57="","",IFERROR(Enquiry!D57,"")) | G57: =IF(Enquiry!B57="","",IFERROR(Enquiry!K57,""))
A58: =IF(Enquiry!B58="","",IFERROR(Enquiry!C58,"")) | B58: =IF(Enquiry!B58="","",IFERROR(Enquiry!D58,"")) | G58: =IF(Enquiry!B58="","",IFERROR(Enquiry!K58,""))
A59: =IF(Enquiry!B59="","",IFERROR(Enquiry!C59,"")) | B59: =IF(Enquiry!B59="","",IFERROR(Enquiry!D59,"")) | G59: =IF(Enquiry!B59="","",IFERROR(Enquiry!K59,""))
A60: =IF(Enquiry!B60="","",IFERROR(Enquiry!C60,"")) | B60: =IF(Enquiry!B60="","",IFERROR(Enquiry!D60,"")) | G60: =IF(Enquiry!B60="","",IFERROR(Enquiry!K60,""))
A61: =IF(Enquiry!B61="","",IFERROR(Enquiry!C61,"")) | B61: =IF(Enquiry!B61="","",IFERROR(Enquiry!D61,"")) | G61: =IF(Enquiry!B61="","",IFERROR(Enquiry!K61,""))
A62: =IF(Enquiry!B62="","",IFERROR(Enquiry!C62,"")) | B62: =IF(Enquiry!B62="","",IFERROR(Enquiry!D62,"")) | G62: =IF(Enquiry!B62="","",IFERROR(Enquiry!K62,""))
... A502: =IF(Enquiry!B502="","",IFERROR(Enquiry!C502,"")) | B502: =IF(Enquiry!B502="","",IFERROR(Enquiry!D502,"")) | G502: =IF(Enquiry!B502="","",IFERROR(Enquiry!K502,""))
